strip_hidden_form_values/__init__.py
strip_hidden_form_values/cli.py
strip_hidden_form_values-0.2.1.dist-info/LICENSE
strip_hidden_form_values-0.2.1.dist-info/METADATA
strip_hidden_form_values-0.2.1.dist-info/WHEEL
strip_hidden_form_values-0.2.1.dist-info/entry_points.txt
strip_hidden_form_values-0.2.1.dist-info/top_level.txt
strip_hidden_form_values-0.2.1.dist-info/RECORD
