Metadata-Version: 2.1
Name: strip-hidden-form-values
Version: 0.2.1
Summary: CLI tool for stripping hidden form values from an HTML document
Home-page: https://github.com/simonw/strip-hidden-form-values
Author: Simon Willison
License: Apache License, Version 2.0
Project-URL: Issues, https://github.com/simonw/strip-hidden-form-values/issues
Project-URL: CI, https://github.com/simonw/strip-hidden-form-values/actions
Project-URL: Changelog, https://github.com/simonw/strip-hidden-form-values/releases
Platform: UNKNOWN
Requires-Python: >=3.6
License-File: LICENSE
Requires-Dist: click
Provides-Extra: test
Requires-Dist: pytest ; extra == 'test'
